zap/__init__.py
zap/__main__.py
zap/utils.py
zap/zap.py
zap-2.1.dist-info/LICENSE
zap-2.1.dist-info/METADATA
zap-2.1.dist-info/WHEEL
zap-2.1.dist-info/entry_points.txt
zap-2.1.dist-info/top_level.txt
zap-2.1.dist-info/RECORD
