Metadata-Version: 2.1
Name: zap
Version: 2.1
Summary: ZAP (the Zurich Atmosphere Purge) is a high precision sky subtraction tool.
Home-page: https://github.com/musevlt/zap
Author: Kurt Soto, Simon Conseil
Author-email: simon.conseil@univ-lyon1.fr
License: MIT License
Keywords: astronomy,astrophysics,science,muse,vlt,sky subtraction
Platform: UNKNOWN
Classifier: Development Status :: 5 - Production/Stable
Classifier: Intended Audience :: Science/Research
Classifier: License :: OSI Approved :: MIT License
Classifier: Operating System :: OS Independent
Classifier: Programming Language :: Python :: 3
Classifier: Programming Language :: Python :: 3.5
Classifier: Programming Language :: Python :: 3.6
Classifier: Programming Language :: Python :: 3.7
Classifier: Programming Language :: Python :: Implementation :: CPython
Classifier: Topic :: Scientific/Engineering :: Astronomy
Classifier: Topic :: Scientific/Engineering :: Physics
Requires-Python: >=3.5
Provides-Extra: plot
